fppanalysis/__init__.py
fppanalysis/binning_container.py
fppanalysis/conditional_averaging.py
fppanalysis/conditional_averaging_2d.py
fppanalysis/correlation_function.py
fppanalysis/deconvolution_methods.py
fppanalysis/distributions.py
fppanalysis/estimate_hurst.py
fppanalysis/excess_statistics.py
fppanalysis/kf_spectra.py
fppanalysis/parameter_estimation_ECF.py
fppanalysis/peak_detection.py
fppanalysis/random_phase.py
fppanalysis/running_moments.py
fppanalysis-0.2.0.dist-info/LICENSE
fppanalysis-0.2.0.dist-info/METADATA
fppanalysis-0.2.0.dist-info/WHEEL
fppanalysis-0.2.0.dist-info/RECORD
